ankita_notes_cli-0.1.2.dist-info/licenses/LICENSE
notes_cli/__init__.py
notes_cli/cli.py
ankita_notes_cli-0.1.2.dist-info/METADATA
ankita_notes_cli-0.1.2.dist-info/WHEEL
ankita_notes_cli-0.1.2.dist-info/entry_points.txt
ankita_notes_cli-0.1.2.dist-info/top_level.txt
ankita_notes_cli-0.1.2.dist-info/RECORD
